{"nodes": [{"id": "users_yashmody_work_code_coder_dept_deploy_backend_scripts_list_media_py", "label": "list_media.py", "file_type": "code", "source_file": "backend/scripts/list_media.py", "source_location": "L1"}, {"id": "scripts_list_media_url_for", "label": "url_for()", "file_type": "code", "source_file": "backend/scripts/list_media.py", "source_location": "L28"}, {"id": "scripts_list_media_fmt_size", "label": "fmt_size()", "file_type": "code", "source_file": "backend/scripts/list_media.py", "source_location": "L38"}, {"id": "scripts_list_media_main", "label": "main()", "file_type": "code", "source_file": "backend/scripts/list_media.py", "source_location": "L46"}, {"id": "scripts_list_media_rationale_1", "label": "List all media in PostgreSQL and print their streaming URLs.  Usage:     python", "file_type": "rationale", "source_file": "backend/scripts/list_media.py", "source_location": "L1"}], "edges": [{"source": "users_yashmody_work_code_coder_dept_deploy_backend_scripts_list_media_py", "target": "argparse", "relation": "imports", "context": "import", "confidence": "EXTRACTED", "source_file": "backend/scripts/list_media.py", "source_location": "L13", "weight": 1.0}, {"source": "users_yashmody_work_code_coder_dept_deploy_backend_scripts_list_media_py", "target": "json", "relation": "imports", "context": "import", "confidence": "EXTRACTED", "source_file": "backend/scripts/list_media.py", "source_location": "L14", "weight": 1.0}, {"source": "users_yashmody_work_code_coder_dept_deploy_backend_scripts_list_media_py", "target": "os", "relation": "imports", "context": "import", "confidence": "EXTRACTED", "source_file": "backend/scripts/list_media.py", "source_location": "L15", "weight": 1.0}, {"source": "users_yashmody_work_code_coder_dept_deploy_backend_scripts_list_media_py", "target": "sys", "relation": "imports", "context": "import", "confidence": "EXTRACTED", "source_file": "backend/scripts/list_media.py", "source_location": "L16", "weight": 1.0}, {"source": "users_yashmody_work_code_coder_dept_deploy_backend_scripts_list_media_py", "target": "sqlalchemy", "relation": "imports_from", "context": "import", "confidence": "EXTRACTED", "source_file": "backend/scripts/list_media.py", "source_location": "L21", "weight": 1.0}, {"source": "users_yashmody_work_code_coder_dept_deploy_backend_scripts_list_media_py", "target": "app_core", "relation": "imports_from", "context": "import", "confidence": "EXTRACTED", "source_file": "backend/scripts/list_media.py", "source_location": "L23", "weight": 1.0}, {"source": "users_yashmody_work_code_coder_dept_deploy_backend_scripts_list_media_py", "target": "app_core_db", "relation": "imports_from", "context": "import", "confidence": "EXTRACTED", "source_file": "backend/scripts/list_media.py", "source_location": "L24", "weight": 1.0}, {"source": "users_yashmody_work_code_coder_dept_deploy_backend_scripts_list_media_py", "target": "app_core_models", "relation": "imports_from", "context": "import", "confidence": "EXTRACTED", "source_file": "backend/scripts/list_media.py", "source_location": "L25", "weight": 1.0}, {"source": "users_yashmody_work_code_coder_dept_deploy_backend_scripts_list_media_py", "target": "scripts_list_media_url_for", "relation": "contains", "confidence": "EXTRACTED", "source_file": "backend/scripts/list_media.py", "source_location": "L28", "weight": 1.0}, {"source": "users_yashmody_work_code_coder_dept_deploy_backend_scripts_list_media_py", "target": "scripts_list_media_fmt_size", "relation": "contains", "confidence": "EXTRACTED", "source_file": "backend/scripts/list_media.py", "source_location": "L38", "weight": 1.0}, {"source": "users_yashmody_work_code_coder_dept_deploy_backend_scripts_list_media_py", "target": "scripts_list_media_main", "relation": "contains", "confidence": "EXTRACTED", "source_file": "backend/scripts/list_media.py", "source_location": "L46", "weight": 1.0}, {"source": "scripts_list_media_main", "target": "scripts_list_media_url_for", "relation": "calls", "context": "call", "confidence": "EXTRACTED", "source_file": "backend/scripts/list_media.py", "source_location": "L80", "weight": 1.0}, {"source": "scripts_list_media_main", "target": "scripts_list_media_fmt_size", "relation": "calls", "context": "call", "confidence": "EXTRACTED", "source_file": "backend/scripts/list_media.py", "source_location": "L94", "weight": 1.0}, {"source": "scripts_list_media_rationale_1", "target": "users_yashmody_work_code_coder_dept_deploy_backend_scripts_list_media_py", "relation": "rationale_for", "confidence": "EXTRACTED", "source_file": "backend/scripts/list_media.py", "source_location": "L1", "weight": 1.0}], "raw_calls": [{"caller_nid": "scripts_list_media_url_for", "callee": "lower", "is_member_call": true, "source_file": "/Users/yashmody/work/CODE-CODER/dept-deploy/backend/scripts/list_media.py", "source_location": "L29"}, {"caller_nid": "scripts_list_media_url_for", "callee": "startswith", "is_member_call": true, "source_file": "/Users/yashmody/work/CODE-CODER/dept-deploy/backend/scripts/list_media.py", "source_location": "L30"}, {"caller_nid": "scripts_list_media_url_for", "callee": "startswith", "is_member_call": true, "source_file": "/Users/yashmody/work/CODE-CODER/dept-deploy/backend/scripts/list_media.py", "source_location": "L32"}, {"caller_nid": "scripts_list_media_main", "callee": "ArgumentParser", "is_member_call": true, "source_file": "/Users/yashmody/work/CODE-CODER/dept-deploy/backend/scripts/list_media.py", "source_location": "L47"}, {"caller_nid": "scripts_list_media_main", "callee": "add_argument", "is_member_call": true, "source_file": "/Users/yashmody/work/CODE-CODER/dept-deploy/backend/scripts/list_media.py", "source_location": "L48"}, {"caller_nid": "scripts_list_media_main", "callee": "add_argument", "is_member_call": true, "source_file": "/Users/yashmody/work/CODE-CODER/dept-deploy/backend/scripts/list_media.py", "source_location": "L53"}, {"caller_nid": "scripts_list_media_main", "callee": "parse_args", "is_member_call": true, "source_file": "/Users/yashmody/work/CODE-CODER/dept-deploy/backend/scripts/list_media.py", "source_location": "L58"}, {"caller_nid": "scripts_list_media_main", "callee": "init_db", "is_member_call": false, "source_file": "/Users/yashmody/work/CODE-CODER/dept-deploy/backend/scripts/list_media.py", "source_location": "L60"}, {"caller_nid": "scripts_list_media_main", "callee": "get_session", "is_member_call": false, "source_file": "/Users/yashmody/work/CODE-CODER/dept-deploy/backend/scripts/list_media.py", "source_location": "L61"}, {"caller_nid": "scripts_list_media_main", "callee": "scalars", "is_member_call": true, "source_file": "/Users/yashmody/work/CODE-CODER/dept-deploy/backend/scripts/list_media.py", "source_location": "L62"}, {"caller_nid": "scripts_list_media_main", "callee": "order_by", "is_member_call": true, "source_file": "/Users/yashmody/work/CODE-CODER/dept-deploy/backend/scripts/list_media.py", "source_location": "L63"}, {"caller_nid": "scripts_list_media_main", "callee": "select", "is_member_call": false, "source_file": "/Users/yashmody/work/CODE-CODER/dept-deploy/backend/scripts/list_media.py", "source_location": "L63"}, {"caller_nid": "scripts_list_media_main", "callee": "desc", "is_member_call": true, "source_file": "/Users/yashmody/work/CODE-CODER/dept-deploy/backend/scripts/list_media.py", "source_location": "L63"}, {"caller_nid": "scripts_list_media_main", "callee": "isoformat", "is_member_call": true, "source_file": "/Users/yashmody/work/CODE-CODER/dept-deploy/backend/scripts/list_media.py", "source_location": "L79"}, {"caller_nid": "scripts_list_media_main", "callee": "dumps", "is_member_call": true, "source_file": "/Users/yashmody/work/CODE-CODER/dept-deploy/backend/scripts/list_media.py", "source_location": "L84"}, {"caller_nid": "scripts_list_media_main", "callee": "startswith", "is_member_call": true, "source_file": "/Users/yashmody/work/CODE-CODER/dept-deploy/backend/scripts/list_media.py", "source_location": "L103"}, {"caller_nid": "scripts_list_media_main", "callee": "startswith", "is_member_call": true, "source_file": "/Users/yashmody/work/CODE-CODER/dept-deploy/backend/scripts/list_media.py", "source_location": "L105"}]}