{"nodes": [{"id": "users_yashmody_work_code_coder_dept_deploy_docs_site_docusaurus_site_storage_json", "label": "site-storage.json", "file_type": "code", "source_file": "docs-site/.docusaurus/site-storage.json", "source_location": "L1"}, {"id": "docusaurus_site_storage_type", "label": "type", "file_type": "code", "source_file": "docs-site/.docusaurus/site-storage.json", "source_location": "L2"}, {"id": "docusaurus_site_storage_namespace", "label": "namespace", "file_type": "code", "source_file": "docs-site/.docusaurus/site-storage.json", "source_location": "L3"}], "edges": [{"source": "users_yashmody_work_code_coder_dept_deploy_docs_site_docusaurus_site_storage_json", "target": "docusaurus_site_storage_type", "relation": "contains", "confidence": "EXTRACTED", "source_file": "docs-site/.docusaurus/site-storage.json", "source_location": "L2", "weight": 1.0}, {"source": "users_yashmody_work_code_coder_dept_deploy_docs_site_docusaurus_site_storage_json", "target": "docusaurus_site_storage_namespace", "relation": "contains", "confidence": "EXTRACTED", "source_file": "docs-site/.docusaurus/site-storage.json", "source_location": "L3", "weight": 1.0}]}